gic_calculator/__init__.py
gic_calculator/gic_difference.py
gic_calculator/gic_plotting.py
gic_calculator/interest_calculator.py
gic_calculator-4.0.0.dist-info/LICENSE
gic_calculator-4.0.0.dist-info/METADATA
gic_calculator-4.0.0.dist-info/WHEEL
gic_calculator-4.0.0.dist-info/RECORD
