Metadata-Version: 2.1
Name: gic_calculator
Version: 4.0.0
Summary: CalculateGIC interets and payout with comparison and plots.
License: MIT
Author: Tony Shum, Ruocong Sun, Alysen Townsley
Requires-Python: >=3.9,<4.0
Classifier: License :: OSI Approved :: MIT License
Classifier: Programming Language :: Python :: 3
Classifier: Programming Language :: Python :: 3.9
Classifier: Programming Language :: Python :: 3.10
Classifier: Programming Language :: Python :: 3.11
Classifier: Programming Language :: Python :: 3.12
Requires-Dist: altair (>=5.2.0,<6.0.0)
Requires-Dist: pandas (>=2.1.4,<3.0.0)
